qrandom/__init__.py
qrandom-1.7.dist-info/METADATA
qrandom-1.7.dist-info/WHEEL
qrandom-1.7.dist-info/top_level.txt
qrandom-1.7.dist-info/RECORD
