Metadata-Version: 2.1
Name: qrandom
Version: 1.7
Summary: This repository contains the source code of research paper titled: "A Generalized Quantum Algorithm for Assuring Fairness in Random Selection Among 2ⁿ Participants."
Home-page: https://github.com/mr-ravin/QrandomSelection
Author: Ravin Kumar
Author-email: mr.ravin_kumar@hotmail.com
Keywords: Quantum Algorithm,Quantum Fairness,One to One,Quantum Random Number,Random Selection,Lucky Draw
Classifier: Programming Language :: Python :: 3
Classifier: License :: OSI Approved :: MIT License
Classifier: Operating System :: OS Independent
Requires-Dist: qiskit ==0.46.0
Requires-Dist: pylatexenc ==2.10
